ride/__init__.py
ride/_version.py
ride/baseline.py
ride/cfg.py
ride/correct.py
ride/detrend.py
ride/filtering.py
ride/helpers.py
ride/interp2d.py
ride/iter.py
ride/median2d.py
ride/results.py
ride/ride.py
ride/tukey.py
ride/tests/__init__.py
ride/tests/sine.py
ride/tests/test.py
eeg_ride-0.3.0.dist-info/LICENSE
eeg_ride-0.3.0.dist-info/METADATA
eeg_ride-0.3.0.dist-info/WHEEL
eeg_ride-0.3.0.dist-info/top_level.txt
eeg_ride-0.3.0.dist-info/RECORD
