Metadata-Version: 2.1
Name: eeg-ride
Version: 0.3.0
Summary: Removing speech artifacts from EEG data using Residue Iteration Decomposition (RIDE)
Home-page: https://github.com/kirstenstark/eeg-ride
Author: Kirsten Stark, Alexander Enge
Author-email: kirsten.stark@hu-berlin.de, alexander.enge@hu-berlin.de
Project-URL: Issue trackers, https://github.com/kirstenstark/eeg-ride/issues
Classifier: Programming Language :: Python :: 3.8
Classifier: Programming Language :: Python :: 3.9
Classifier: Programming Language :: Python :: 3.10
Classifier: Programming Language :: Python :: 3.11
Classifier: License :: OSI Approved :: MIT License
Classifier: Operating System :: OS Independent
Requires-Python: >=3.8
License-File: LICENSE
Requires-Dist: matplotlib
Requires-Dist: numpy
Requires-Dist: scipy
